interviewer/__init__.py
interviewer/bot.py
interviewer-0.3.dist-info/METADATA
interviewer-0.3.dist-info/WHEEL
interviewer-0.3.dist-info/top_level.txt
interviewer-0.3.dist-info/RECORD
