Metadata-Version: 2.1
Name: interviewer
Version: 0.3
Summary: Preparation Bot for Job Interviews
Home-page: UNKNOWN
Author: Lukas Jan Stroemsdoerfer
Author-email: ljstroemsdoerfer@gmail.com
License: MIT
Platform: UNKNOWN
